application/__init__.py
application/core/__init__.py
application/core/parser_data.py
application/core/db/__init__.py
application/core/db/create_db_table.py
application/core/jobs/__init__.py
application/core/jobs/get_masked_or_deleted_db.py
test2/__init__.py
test2/app.py
my_masker1-0.1.4.dist-info/METADATA
my_masker1-0.1.4.dist-info/WHEEL
my_masker1-0.1.4.dist-info/entry_points.txt
my_masker1-0.1.4.dist-info/top_level.txt
my_masker1-0.1.4.dist-info/RECORD
